Workbook

Sheet HISTORICALS
A1: INCOME STATEMENT | B1: 2025 | C1: 2024 | D1: 2023
A2: REVENUE | B2: 275235000 | C2: 254453000 | D2: 242290000
A3: COGS | B3: 239886000 | C3: 222358000 | D3: 212586000 | J3: TAX RATE | K3: 0.24
J4: REVENUE GROWTH RATE | K4: 0.06
A5: GROSS PROFIT | B5: =B2-B3 -> 35349000 | C5: =C2-C3 -> 32095000 | D5: =D2-D3 -> 29704000 | J5: EXPENSES GROWTH RATE | K5: 0.04
A6: OPERATING EXPENSE | B6: 24966000 | C6: 22810000 | D6: 21590000 | J6: DISCOUNT RATE | K6: =K18 -> 0.076285
A7: DEPRECITATION | B7: 2426000 | C7: 2237000 | D7: 2048000
J8: Re = RISK FREE RATE + (BETA(EQ.RISK PREMIUM
A9: OPERATING INCOME | B9: =B5-B6-B7 -> 7957000 | C9: =C5-C6-C7 -> 7048000 | D9: =D5-D6-D7 -> 6066000
A10: OTHER INCOME | B10: 0 | C10: 0 | D10: 0 | J10: RISK FREE RATE | K10: 0.042
J11: BETA | K11: 0.66
A12: EBIT | B12: =B9-B10 -> 7957000 | C12: =C9-C10 -> 7048000 | D12: =D9-D10 -> 6066000 | J12: EQ RISK PREMIUM | K12: 0.055
A13: INTEREST | B13: 154000 | C13: 169000 | D13: 160000 | J13: Re | K13: =K10+(K11*K12) -> 0.0783
J14: cost of debt | K14: 0.05
A15: TAXABLE INCOME | B15: =B12-B13 -> 7803000 | C15: =C12-C13 -> 6879000 | D15: =D12-D13 -> 5906000 | J15: We | K15: 0.95
J16: Wd | K16: 0.05
A17: TAXES | B17: =B15*$K$3 -> 1872720 | C17: =C15*$K$3 -> 1650960 | D17: =D15*$K$3 -> 1417440
A18: NET INCOME | B18: =B15-B17 -> 5930280 | C18: =C15-C17 -> 5228040 | D18: =D15-D17 -> 4488560 | J18: WACC | K18: =(K15*K13)+(K16*K14*(1-K3)) -> 0.076285
A20: OPERATING CASH FLOW | B20: =B18+B10+B7 -> 8356280 | C20: =C18+C10+C7 -> 7465040 | D20: =D18+D10+D7 -> 6536560
A21: CAPEX | B21: 5498000 | C21: 4710000 | D21: 4323000
A23: TOTAL CASH FLOW | B23: =B20-B21 -> 2858280 | C23: =C20-C21 -> 2755040 | D23: =D20-D21 -> 2213560

Sheet PROJECTIONS
A1: INCOME STATEMENT | B1: 2025 | C1: 2026 | D1: 2027 | E1: 2028 | F1: 2029
A2: REVENUE | B2: =HISTORICALS!$B$2 -> 275235000 | C2: =B2*(1+HISTORICALS!$K$6) -> 2.962313e+08 | D2: =C2*(1+HISTORICALS!$K$6) -> 3.1882931e+08 | E2: =D2*(1+HISTORICALS!$K$6) -> 3.431512e+08 | F2: =E2*(1+HISTORICALS!$K$6) -> 3.6932849e+08
A3: COGS | B3: =HISTORICALS!$B$3 -> 239886000 | C3: =B3*(1+HISTORICALS!$K$5) -> 249481440 | D3: =C3*(1+HISTORICALS!$K$5) -> 2.594607e+08 | E3: =D3*(1+HISTORICALS!$K$5) -> 2.6983913e+08 | F3: =E3*(1+HISTORICALS!$K$5) -> 2.8063269e+08
A5: GROSS PROFIT | B5: =B2-B3 -> 35349000 | C5: =C2-C3 -> 46749862 | D5: =D2-D3 -> 59368609 | E5: =E2-E3 -> 73312075 | F5: =F2-F3 -> 88695799
A6: OPERATING EXPENSE | B6: =HISTORICALS!$B$6 -> 24966000 | C6: =B6*(1+HISTORICALS!$K$5) -> 25964640 | D6: =C6*(1+HISTORICALS!$K$5) -> 27003226 | E6: =D6*(1+HISTORICALS!$K$5) -> 28083355 | F6: =E6*(1+HISTORICALS!$K$5) -> 29206689
A7: DEPRECITATION | B7: =HISTORICALS!$B$7 -> 2426000 | C7: =B7*(1+HISTORICALS!$K$5) -> 2523040 | D7: =C7*(1+HISTORICALS!$K$5) -> 2623961.6 | E7: =D7*(1+HISTORICALS!$K$5) -> 2728920.1 | F7: =E7*(1+HISTORICALS!$K$5) -> 2838076.9
A9: OPERATING INCOME | B9: =B5-B6-B7 -> 7957000 | C9: =C5-C6-C7 -> 18262182 | D9: =D5-D6-D7 -> 29741422 | E9: =E5-E6-E7 -> 42499800 | F9: =F5-F6-F7 -> 56651034
A10: OTHER INCOME | B10: =0 -> 0 | C10: =0 -> 0 | D10: =0 -> 0 | E10: =0 -> 0 | F10: =0 -> 0
A12: EBIT | B12: =B9-B10 -> 7957000 | C12: =C9-C10 -> 18262182 | D12: =D9-D10 -> 29741422 | E12: =E9-E10 -> 42499800 | F12: =F9-F10 -> 56651034
A13: INTEREST | B13: =HISTORICALS!$B$13 -> 154000 | C13: =B13*(1+HISTORICALS!$K$5) -> 160160 | D13: =C13*(1+HISTORICALS!$K$5) -> 166566.4 | E13: =D13*(1+HISTORICALS!$K$5) -> 173229.06 | F13: =E13*(1+HISTORICALS!$K$5) -> 180158.22
A15: TAXABLE INCOME | B15: =B12-B13 -> 7803000 | C15: =C12-C13 -> 18102022 | D15: =D12-D13 -> 29574856 | E15: =E12-E13 -> 42326571 | F15: =F12-F13 -> 56470875
A17: TAXES | B17: =B15*HISTORICALS!$K$3 -> 1872720 | C17: =C15*HISTORICALS!$K$3 -> 4344485.3 | D17: =D15*HISTORICALS!$K$3 -> 7097965.4 | E17: =E15*HISTORICALS!$K$3 -> 10158377 | F17: =F15*HISTORICALS!$K$3 -> 13553010
A18: NET INCOME | B18: =B15-B17 -> 5930280 | C18: =C15-C17 -> 13757537 | D18: =D15-D17 -> 22476890 | E18: =E15-E17 -> 32168194 | F18: =F15-F17 -> 42917865
A20: OPERATING CASH FLOW | B20: =B18+B10+B7 -> 8356280 | C20: =C18+C10+C7 -> 16280577 | D20: =D18+D10+D7 -> 25100852 | E20: =E18+E10+E7 -> 34897114 | F20: =F18+F10+F7 -> 45755942
A21: CAPEX | B21: =HISTORICALS!$B$21 -> 5498000 | C21: =B21*(1+HISTORICALS!$K$5) -> 5717920 | D21: =C21*(1+HISTORICALS!$K$5) -> 5946636.8 | E21: =D21*(1+HISTORICALS!$K$5) -> 6184502.3 | F21: =E21*(1+HISTORICALS!$K$5) -> 6431882.4
A23: TOTAL CASH FLOW | B23: =B20-B21 -> 2858280 | C23: =C20-C21 -> 10562657 | D23: =D20-D21 -> 19154215 | E23: =E20-E21 -> 28712612 | F23: =F20-F21 -> 39324060
A24: PV(TCF) | B24: =B23/(1+HISTORICALS!$K$6)^(B1-2024) -> 2655690.6 | C24: =C23/(1+HISTORICALS!$K$6)^(C1-B1) -> 9813996 | D24: =D23/(1+HISTORICALS!$K$6)^(D1-C1) -> 17796601 | E24: =E23/(1+HISTORICALS!$K$6)^(E1-D1) -> 26677518 | F24: =F23/(1+HISTORICALS!$K$6)^(F1-E1) -> 36536846
A26: NPV | B26: =NPV(HISTORICALS!K6,PROJECTIONS!B24:F24) -> 70393279

Sheet VALUATION
A1: FCF | B1: =SUM(PROJECTIONS!B24:F24) -> 93480652
A2: NPV | B2: =PROJECTIONS!B26 -> 70393279
A3: TERMINAL VALUE | B3: =PROJECTIONS!F23*(1+0.03)/(HISTORICALS!K18-0.03) -> 8.7509521e+08
A4: PV (TV) | B4: =B3/(1+HISTORICALS!K18)^5 -> 6.0592499e+08
A5: ENTERPRISE VALUE | B5: =B4+B2 -> 6.7631827e+08
A6: CASH AND EQUIVALENTS | B6: 15284000
A7: DEBT | B7: 8173000
A8: EQUITY VALUE | B8: =B5+B6-B7 -> 6.8342927e+08
A9: SHARES O/S | B9: 444509.75
A10: SHARE PRICE | B10: =B8/B9 -> 1537.4899
